BuyCoin/__init__.py
BuyCoin/config.py
BuyCoin/manager.py
BuyCoin/utils.py
BuyCoin/objects/__init__.py
BuyCoin/objects/errors.py
BuyCoin/objects/ngnt.py
BuyCoin/objects/p2p.py
BuyCoin/objects/wallet.py
test/__init__.py
python_buycoins_sdk-0.0.4.dist-info/LICENSE
python_buycoins_sdk-0.0.4.dist-info/METADATA
python_buycoins_sdk-0.0.4.dist-info/WHEEL
python_buycoins_sdk-0.0.4.dist-info/top_level.txt
python_buycoins_sdk-0.0.4.dist-info/RECORD
