Metadata-Version: 2.1
Name: python-buycoins-sdk
Version: 0.0.4
Summary: BUYCOINS SDK
Home-page: https://github.com/NerdPraise/python-buycoin
Author: Praise Ajayi
Author-email: praiseajayi2@gmail.com
License: MIT
Keywords: python,SDK,Buycoins
Platform: UNKNOWN
Classifier: Programming Language :: Python :: 2
Classifier: Programming Language :: Python :: 3
Requires-Python: >=3.0
Requires-Dist: python-graphql-client
Requires-Dist: requests
Requires-Dist: python-decouple
Requires-Dist: jsonpickle
